boston_harbor_ferries/__init__.py
boston_harbor_ferries/aprs_parser.py
boston_harbor_ferries/cli.py
boston_harbor_ferries/client.py
boston_harbor_ferries/config.py
boston_harbor_ferries/mcp_server.py
boston_harbor_ferries/schemas.py
boston_harbor_ferries/vessels.py
boston_harbor_ferries-0.1.0.dist-info/METADATA
boston_harbor_ferries-0.1.0.dist-info/WHEEL
boston_harbor_ferries-0.1.0.dist-info/entry_points.txt
boston_harbor_ferries-0.1.0.dist-info/RECORD
