Metadata-Version: 2.4
Name: boston-harbor-ferries
Version: 0.1.0
Summary: APRS-based Boston Harbor commuter ferry tracker with MCP server
Project-URL: Homepage, https://github.com/aygp-dr/boston-harbor-ferries
Project-URL: Repository, https://github.com/aygp-dr/boston-harbor-ferries.git
Project-URL: Issues, https://github.com/aygp-dr/boston-harbor-ferries/issues
Author-email: Aidan Pace <apace@defrecord.com>
Maintainer-email: Aidan Pace <apace@defrecord.com>
License: MIT
Keywords: aprs,boston,ferry,harbor,marine,mcp,tracker
Classifier: Development Status :: 3 - Alpha
Classifier: Intended Audience :: Developers
Classifier: License :: OSI Approved :: MIT License
Classifier: Programming Language :: Python :: 3
Classifier: Programming Language :: Python :: 3.10
Classifier: Programming Language :: Python :: 3.11
Classifier: Programming Language :: Python :: 3.12
Classifier: Topic :: Communications :: Ham Radio
Classifier: Topic :: Scientific/Engineering :: GIS
Requires-Python: >=3.10
Requires-Dist: click>=8.1.7
Requires-Dist: diskcache>=5.6.3
Requires-Dist: httpx>=0.26.0
Requires-Dist: mcp>=0.9.0
Requires-Dist: pydantic-settings>=2.1.0
Requires-Dist: pydantic>=2.5.0
Requires-Dist: rich>=13.7.0
Provides-Extra: dev
Requires-Dist: pytest-asyncio>=0.21.0; extra == 'dev'
Requires-Dist: pytest-httpx>=0.27.0; extra == 'dev'
Requires-Dist: pytest>=7.4.0; extra == 'dev'
Provides-Extra: viz
Requires-Dist: matplotlib>=3.7.0; extra == 'viz'
Requires-Dist: numpy>=1.24.0; extra == 'viz'
Requires-Dist: pandas>=2.0.0; extra == 'viz'
Requires-Dist: seaborn>=0.13.0; extra == 'viz'
